Workbook
Name Slicer_Gender: #N/A
Name Slicer_What_are_your_savings_objectives?: #N/A
Name Slicer_Source: #N/A
Name Slicer_Expect: #N/A

Sheet Sheet1
A1: Gender | B1: age | C1: Investment_Avenues | D1: Mutual_Funds | E1: Equity_Market | F1: Debentures | G1: Government_Bonds | H1: Fixed_Deposits | I1: PPF | J1: Gold | K1: Stock_Marktet | L1: Factor | M1: Objective | N1: Purpose | O1: Duration | P1: Invest_Monitor | Q1: Expect | R1: Avenue | S1: What are your savings objectives? | T1: Reason_Equity | U1: Reason_Mutual | V1: Reason_Bonds | W1: Reason_FD | X1: Source
A2: Female | B2: 34 | C2: Yes | D2: 1 | E2: 2 | F2: 5 | G2: 3 | H2: 7 | I2: 6 | J2: 4 | K2: Yes | L2: Returns | M2: Capital Appreciation | N2: Wealth Creation | O2: 1-3 years | P2: Monthly | Q2: 20%-30% | R2: Mutual Fund | S2: Retirement Plan | T2: Capital Appreciation | U2: Better Returns | V2: Safe Investment | W2: Fixed Returns | X2: Newspapers and Magazines
A3: Female | B3: 23 | C3: Yes | D3: 4 | E3: 3 | F3: 2 | G3: 1 | H3: 5 | I3: 6 | J3: 7 | K3: No | L3: Locking Period | M3: Capital Appreciation | N3: Wealth Creation | O3: More than 5 years | P3: Weekly | Q3: 20%-30% | R3: Mutual Fund | S3: Health Care | T3: Dividend | U3: Better Returns | V3: Safe Investment | W3: High Interest Rates | X3: Financial Consultants
A4: Male | B4: 30 | C4: Yes | D4: 3 | E4: 6 | F4: 4 | G4: 2 | H4: 5 | I4: 1 | J4: 7 | K4: Yes | L4: Returns | M4: Capital Appreciation | N4: Wealth Creation | O4: 3-5 years | P4: Daily | Q4: 20%-30% | R4: Equity | S4: Retirement Plan | T4: Capital Appreciation | U4: Tax Benefits | V4: Assured Returns | W4: Fixed Returns | X4: Television
A5: Male | B5: 22 | C5: Yes | D5: 2 | E5: 1 | F5: 3 | G5: 7 | H5: 6 | I5: 4 | J5: 5 | K5: Yes | L5: Returns | M5: Income | N5: Wealth Creation | O5: Less than 1 year | P5: Daily | Q5: 10%-20% | R5: Equity | S5: Retirement Plan | T5: Dividend | U5: Fund Diversification | V5: Tax Incentives | W5: High Interest Rates | X5: Internet
A6: Female | B6: 24 | C6: No | D6: 2 | E6: 1 | F6: 3 | G6: 6 | H6: 4 | I6: 5 | J6: 7 | K6: No | L6: Returns | M6: Income | N6: Wealth Creation | O6: Less than 1 year | P6: Daily | Q6: 20%-30% | R6: Equity | S6: Retirement Plan | T6: Capital Appreciation | U6: Better Returns | V6: Safe Investment | W6: Risk Free | X6: Internet
A7: Female | B7: 24 | C7: No | D7: 7 | E7: 5 | F7: 4 | G7: 6 | H7: 3 | I7: 1 | J7: 2 | K7: No | L7: Risk | M7: Capital Appreciation | N7: Wealth Creation | O7: 1-3 years | P7: Daily | Q7: 30%-40% | R7: Mutual Fund | S7: Retirement Plan | T7: Liquidity | U7: Fund Diversification | V7: Safe Investment | W7: Risk Free | X7: Internet
A8: Female | B8: 27 | C8: Yes | D8: 3 | E8: 6 | F8: 4 | G8: 2 | H8: 5 | I8: 1 | J8: 7 | K8: Yes | L8: Returns | M8: Capital Appreciation | N8: Wealth Creation | O8: 3-5 years | P8: Monthly | Q8: 20%-30% | R8: Equity | S8: Retirement Plan | T8: Capital Appreciation | U8: Better Returns | V8: Assured Returns | W8: High Interest Rates | X8: Financial Consultants
A9: Male | B9: 21 | C9: Yes | D9: 2 | E9: 3 | F9: 7 | G9: 4 | H9: 6 | I9: 1 | J9: 5 | K9: Yes | L9: Risk | M9: Capital Appreciation | N9: Wealth Creation | O9: 3-5 years | P9: Monthly | Q9: 20%-30% | R9: Mutual Fund | S9: Retirement Plan | T9: Capital Appreciation | U9: Better Returns | V9: Assured Returns | W9: Risk Free | X9: Newspapers and Magazines
A10: Male | B10: 35 | C10: Yes | D10: 2 | E10: 4 | F10: 7 | G10: 5 | H10: 3 | I10: 1 | J10: 6 | K10: Yes | L10: Returns | M10: Growth | N10: Savings for Future | O10: 1-3 years | P10: Weekly | Q10: 20%-30% | R10: Equity | S10: Retirement Plan | T10: Capital Appreciation | U10: Fund Diversification | V10: Safe Investment | W10: Fixed Returns | X10: Television
A11: Male | B11: 31 | C11: Yes | D11: 1 | E11: 3 | F11: 7 | G11: 4 | H11: 5 | I11: 2 | J11: 6 | K11: Yes | L11: Returns | M11: Capital Appreciation | N11: Wealth Creation | O11: 3-5 years | P11: Monthly | Q11: 30%-40% | R11: Fixed Deposits | S11: Retirement Plan | T11: Capital Appreciation | U11: Fund Diversification | V11: Assured Returns | W11: Fixed Returns | X11: Newspapers and Magazines
A12: Female | B12: 35 | C12: Yes | D12: 2 | E12: 4 | F12: 7 | G12: 5 | H12: 3 | I12: 1 | J12: 6 | K12: Yes | L12: Risk | M12: Growth | N12: Savings for Future | O12: 3-5 years | P12: Monthly | Q12: 20%-30% | R12: Mutual Fund | S12: Retirement Plan | T12: Capital Appreciation | U12: Better Returns | V12: Assured Returns | W12: Risk Free | X12: Financial Consultants
A13: Male | B13: 29 | C13: Yes | D13: 2 | E13: 5 | F13: 7 | G13: 6 | H13: 3 | I13: 1 | J13: 4 | K13: Yes | L13: Risk | M13: Capital Appreciation | N13: Wealth Creation | O13: 1-3 years | P13: Monthly | Q13: 20%-30% | R13: Mutual Fund | S13: Retirement Plan | T13: Capital Appreciation | U13: Fund Diversification | V13: Assured Returns | W13: Fixed Returns | X13: Financial Consultants
... A41: Male | B41: 29 | C41: Yes | D41: 4 | E41: 3 | F41: 5 | G41: 7 | H41: 2 | I41: 1 | J41: 6 | K41: Yes | L41: Returns | M41: Capital Appreciation | N41: Wealth Creation | O41: 3-5 years | P41: Monthly | Q41: 20%-30% | R41: Fixed Deposits | S41: Retirement Plan | T41: Dividend | U41: Better Returns | V41: Safe Investment | W41: Fixed Returns | X41: Financial Consultants

Sheet Sheet2
B1: Task 1 : Gender distribution Analysis in Excel
B6: Count of each gender
G7: Gender | H7: Count of Gender
B8: Male | C8: Female | G8: Female | H8: 15
B9: =COUNTIF(Sheet1!A:A,B8) -> 25 | C9: =COUNTIF(Sheet1!A:A,C8) -> 15 | G9: Male | H9: 25
G10: Grand Total | H10: 40

Sheet Sheet3
B1: Task 2 : Investment preferences Analysis in Excel
E5: Equity Reasons | H5: Bonds Reasons
B6: Avenue | C6: Count of Avenue | E6: Row Labels | F6: Count of Reason_Equity | H6: Reason_Bonds | I6: Count of Reason_Bonds | K6: Investment Avenue | L6: =E7 -> Capital Appreciation | M6: =E8 -> Dividend | N6: =E9 -> Liquidity | O6: =E15 -> Better Returns | P6: =E16 -> Fund Diversification | Q6: =E17 -> Tax Benefits | R6: =H7 -> Assured Returns | S6: =H8 -> Safe Investment | T6: =H9 -> Tax Incentives | U6: =H15 -> Fixed Returns | V6: =H16 -> High Interest Rates | W6: =H17 -> Risk Free
B7: Equity | C7: 10 | E7: Capital Appreciation | F7: 30 | H7: Assured Returns | I7: 26 | K7: Equity | L7: =COUNTIFS(Sheet1!$T:$T,L$6) -> 30 | M7: =COUNTIFS(Sheet1!$T:$T,M$6) -> 8 | N7: =COUNTIFS(Sheet1!$T:$T,N$6) -> 2 | O7: =COUNTIFS(Sheet1!$T:$T,O$6) -> 0 | P7: =COUNTIFS(Sheet1!$T:$T,P$6) -> 0 | Q7: =COUNTIFS(Sheet1!$T:$T,Q$6) -> 0 | R7: =COUNTIFS(Sheet1!$T:$T,R$6) -> 0 | S7: =COUNTIFS(Sheet1!$T:$T,S$6) -> 0 | ... W7: =COUNTIFS(Sheet1!$T:$T,W$6) -> 0
B8: Fixed Deposits | C8: 9 | E8: Dividend | F8: 8 | H8: Safe Investment | I8: 13 | K8: Mutual | L8: =COUNTIFS(Sheet1!$U:$U,L$6) -> 0 | M8: =COUNTIFS(Sheet1!$U:$U,M$6) -> 0 | N8: =COUNTIFS(Sheet1!$U:$U,N$6) -> 0 | O8: =COUNTIFS(Sheet1!$U:$U,O$6) -> 24 | P8: =COUNTIFS(Sheet1!$U:$U,P$6) -> 13 | Q8: =COUNTIFS(Sheet1!$U:$U,Q$6) -> 3 | R8: =COUNTIFS(Sheet1!$U:$U,R$6) -> 0 | S8: =COUNTIFS(Sheet1!$U:$U,S$6) -> 0 | ... W8: =COUNTIFS(Sheet1!$U:$U,W$6) -> 0
B9: Mutual Fund | C9: 18 | E9: Liquidity | F9: 2 | H9: Tax Incentives | I9: 1 | K9: Bonds | L9: =COUNTIFS(Sheet1!$V:$V,L$6) -> 0 | M9: =COUNTIFS(Sheet1!$V:$V,M$6) -> 0 | N9: =COUNTIFS(Sheet1!$V:$V,N$6) -> 0 | O9: =COUNTIFS(Sheet1!$V:$V,O$6) -> 0 | P9: =COUNTIFS(Sheet1!$V:$V,P$6) -> 0 | Q9: =COUNTIFS(Sheet1!$V:$V,Q$6) -> 0 | R9: =COUNTIFS(Sheet1!$V:$V,R$6) -> 26 | S9: =COUNTIFS(Sheet1!$V:$V,S$6) -> 13 | ... W9: =COUNTIFS(Sheet1!$V:$V,W$6) -> 0
B10: Public Provident Fund | C10: 3 | E10: Grand Total | F10: 40 | H10: Grand Total | I10: 40 | K10: FD | L10: =COUNTIFS(Sheet1!$W:$W,L$6) -> 0 | M10: =COUNTIFS(Sheet1!$W:$W,M$6) -> 0 | N10: =COUNTIFS(Sheet1!$W:$W,N$6) -> 0 | O10: =COUNTIFS(Sheet1!$W:$W,O$6) -> 0 | P10: =COUNTIFS(Sheet1!$W:$W,P$6) -> 0 | Q10: =COUNTIFS(Sheet1!$W:$W,Q$6) -> 0 | R10: =COUNTIFS(Sheet1!$W:$W,R$6) -> 0 | S10: =COUNTIFS(Sheet1!$W:$W,S$6) -> 0 | ... W10: =COUNTIFS(Sheet1!$W:$W,W$6) -> 19
B11: Grand Total | C11: 40
E13: Mutual Reasons | H13: FD Reasons | K13: =Sheet7!J22 -> 0
E14: Reason_Mutual | F14: Count of Reason_Mutual | H14: Reason_FD | I14: Count of Reason_FD
E15: Better Returns | F15: 24 | H15: Fixed Returns | I15: 18
E16: Fund Diversification | F16: 13 | H16: High Interest Rates | I16: 3
E17: Tax Benefits | F17: 3 | H17: Risk Free | I17: 19
E18: Grand Total | F18: 40 | H18: Grand Total | I18: 40
K20: Avenue | L20: Count of Reason_Bonds | M20: Count of Reason_Equity | N20: Count of Reason_FD | O20: Count of Reason_Mutual
K21: Mutual Fund | L21: 18 | M21: 18 | N21: 18 | O21: 18
K22: Equity | L22: 10 | M22: 10 | N22: 10 | O22: 10
K23: Fixed Deposits | L23: 9 | M23: 9 | N23: 9 | O23: 9
K24: Public Provident Fund | L24: 3 | M24: 3 | N24: 3 | O24: 3
K25: Grand Total | L25: 40 | M25: 40 | N25: 40 | O25: 40

Sheet Sheet4
A1: Task 3 : Objectives and source Analysis in excel
A4: What are your savings objectives? | B4: Count of What are your savings objectives? | F4: Source | G4: Count of Source
A5: Education | B5: 3 | F5: Financial Consultants | G5: 16
A6: Health Care | B6: 13 | F6: Internet | G6: 4
A7: Retirement Plan | B7: 24 | F7: Newspapers and Magazines | G7: 14
A8: Grand Total | B8: 40 | F8: Television | G8: 6
F9: Grand Total | G9: 40

Sheet Sheet5
A1: Task 4: Duration and Expectations Analysis in Excel
B4: Duration | C4: Count of Duration | J4: Expect | K4: Count of Expect
B5: 1-3 years | C5: 18 | J5: 10%-20% | K5: 3
B6: 3-5 years | C6: 19 | J6: 20%-30% | K6: 32
B7: Less than 1 year | C7: 2 | J7: 30%-40% | K7: 5
B8: More than 5 years | C8: 1 | J8: Grand Total | K8: 40
B9: Grand Total | C9: 40

Sheet Sheet6
A1: Task 5: Correlation Analysis in Excel
A5: Age | B5: Duration | C5: Expect | D5: Correlation B\w Age and Duration | AE5: Age | AH5: Expect | AJ5: age | AK5: Duration | AL5: Expect
A6: 34 | B6: 2 | C6: 2 | D6: {=CORREL(A6:A45,B6:B45)} -> 0.02011295 | AE6: 34 | AF6: =IF(Sheet1!O2="1-3 years","2",IF(Sheet1!O2="more than 5 years","5",IF(Sheet1!O2="3-5 years","3","1"))) -> 2 | AG6: =IF(Sheet1!Q2="20%-30%","2",IF(Sheet1!Q2="10%-20%","1",IF(Sheet1!Q2="30%-40%","3"))) -> 2 | AH6: 2 | AJ6: 34 | AK6: 1-3 years | AL6: 20%-30%
A7: 23 | B7: 5 | C7: 2 | AE7: 23 | AF7: =IF(Sheet1!O3="1-3 years","2",IF(Sheet1!O3="more than 5 years","5",IF(Sheet1!O3="3-5 years","3","1"))) -> 5 | AG7: =IF(Sheet1!Q3="20%-30%","2",IF(Sheet1!Q3="10%-20%","1",IF(Sheet1!Q3="30%-40%","3"))) -> 2 | AH7: 2 | AJ7: 23 | AK7: More than 5 years | AL7: 20%-30%
A8: 30 | B8: 3 | C8: 2 | D8: Correlation B\w Age and Expect | AE8: 30 | AF8: =IF(Sheet1!O4="1-3 years","2",IF(Sheet1!O4="more than 5 years","5",IF(Sheet1!O4="3-5 years","3","1"))) -> 3 | AG8: =IF(Sheet1!Q4="20%-30%","2",IF(Sheet1!Q4="10%-20%","1",IF(Sheet1!Q4="30%-40%","3"))) -> 2 | AH8: 2 | AJ8: 30 | AK8: 3-5 years | AL8: 20%-30%
A9: 22 | B9: 1 | C9: 1 | D9: {=CORREL(A6:A45,C6:C45)} -> -0.08960562 | AE9: 22 | AF9: =IF(Sheet1!O5="1-3 years","2",IF(Sheet1!O5="more than 5 years","5",IF(Sheet1!O5="3-5 years","3","1"))) -> 1 | AG9: =IF(Sheet1!Q5="20%-30%","2",IF(Sheet1!Q5="10%-20%","1",IF(Sheet1!Q5="30%-40%","3"))) -> 1 | AH9: 1 | AJ9: 22 | AK9: Less than 1 year | AL9: 10%-20%
A10: 24 | B10: 1 | C10: 2 | AE10: 24 | AF10: =IF(Sheet1!O6="1-3 years","2",IF(Sheet1!O6="more than 5 years","5",IF(Sheet1!O6="3-5 years","3","1"))) -> 1 | AG10: =IF(Sheet1!Q6="20%-30%","2",IF(Sheet1!Q6="10%-20%","1",IF(Sheet1!Q6="30%-40%","3"))) -> 2 | AH10: 2 | AJ10: 24 | AK10: Less than 1 year | AL10: 20%-30%
A11: 24 | B11: 2 | C11: 3 | D11: Correlation B\w Duration and Expect | AE11: 24 | AF11: =IF(Sheet1!O7="1-3 years","2",IF(Sheet1!O7="more than 5 years","5",IF(Sheet1!O7="3-5 years","3","1"))) -> 2 | AG11: =IF(Sheet1!Q7="20%-30%","2",IF(Sheet1!Q7="10%-20%","1",IF(Sheet1!Q7="30%-40%","3"))) -> 3 | AH11: 3 | AJ11: 24 | AK11: 1-3 years | AL11: 30%-40%
A12: 27 | B12: 3 | C12: 2 | D12: {=CORREL(B6:B45,C6:C45)} -> 0.23866719 | AE12: 27 | AF12: =IF(Sheet1!O8="1-3 years","2",IF(Sheet1!O8="more than 5 years","5",IF(Sheet1!O8="3-5 years","3","1"))) -> 3 | AG12: =IF(Sheet1!Q8="20%-30%","2",IF(Sheet1!Q8="10%-20%","1",IF(Sheet1!Q8="30%-40%","3"))) -> 2 | AH12: 2 | AJ12: 27 | AK12: 3-5 years | AL12: 20%-30%
A13: 21 | B13: 3 | C13: 2 | AE13: 21 | AF13: =IF(Sheet1!O9="1-3 years","2",IF(Sheet1!O9="more than 5 years","5",IF(Sheet1!O9="3-5 years","3","1"))) -> 3 | AG13: =IF(Sheet1!Q9="20%-30%","2",IF(Sheet1!Q9="10%-20%","1",IF(Sheet1!Q9="30%-40%","3"))) -> 2 | AH13: 2 | AJ13: 21 | AK13: 3-5 years | AL13: 20%-30%
A14: 35 | B14: 2 | C14: 2 | AE14: 35 | AF14: =IF(Sheet1!O10="1-3 years","2",IF(Sheet1!O10="more than 5 years","5",IF(Sheet1!O10="3-5 years","3","1"))) -> 2 | AG14: =IF(Sheet1!Q10="20%-30%","2",IF(Sheet1!Q10="10%-20%","1",IF(Sheet1!Q10="30%-40%","3"))) -> 2 | AH14: 2 | AJ14: 35 | AK14: 1-3 years | AL14: 20%-30%
A15: 31 | B15: 3 | C15: 3 | D15: Correlation analysis was performed using Excel's CORREL function. The correlation between Age and Investment Duration is 0.020, indicating virtually no relationship. The correlation between Age and Expected Returns is -0.090, indicating a very weak negative relationship. The correlation between Investment Duration and Expected Returns is 0.239, indicating a weak positive relationship. Overall, none of the variables show a strong linear correlation. | AE15: 31 | AF15: =IF(Sheet1!O11="1-3 years","2",IF(Sheet1!O11="more than 5 years","5",IF(Sheet1!O11="3-5 years","3","1"))) -> 3 | AG15: =IF(Sheet1!Q11="20%-30%","2",IF(Sheet1!Q11="10%-20%","1",IF(Sheet1!Q11="30%-40%","3"))) -> 3 | AH15: 3 | AJ15: 31 | AK15: 3-5 years | AL15: 30%-40%
A16: 35 | B16: 3 | C16: 2 | AE16: 35 | AF16: =IF(Sheet1!O12="1-3 years","2",IF(Sheet1!O12="more than 5 years","5",IF(Sheet1!O12="3-5 years","3","1"))) -> 3 | AG16: =IF(Sheet1!Q12="20%-30%","2",IF(Sheet1!Q12="10%-20%","1",IF(Sheet1!Q12="30%-40%","3"))) -> 2 | AH16: 2 | AJ16: 35 | AK16: 3-5 years | AL16: 20%-30%
A17: 29 | B17: 2 | C17: 2 | AE17: 29 | AF17: =IF(Sheet1!O13="1-3 years","2",IF(Sheet1!O13="more than 5 years","5",IF(Sheet1!O13="3-5 years","3","1"))) -> 2 | AG17: =IF(Sheet1!Q13="20%-30%","2",IF(Sheet1!Q13="10%-20%","1",IF(Sheet1!Q13="30%-40%","3"))) -> 2 | AH17: 2 | AJ17: 29 | AK17: 1-3 years | AL17: 20%-30%
A18: 21 | B18: 2 | C18: 2 | AE18: 21 | AF18: =IF(Sheet1!O14="1-3 years","2",IF(Sheet1!O14="more than 5 years","5",IF(Sheet1!O14="3-5 years","3","1"))) -> 2 | AG18: =IF(Sheet1!Q14="20%-30%","2",IF(Sheet1!Q14="10%-20%","1",IF(Sheet1!Q14="30%-40%","3"))) -> 2 | AH18: 2 | AJ18: 21 | AK18: 1-3 years | AL18: 20%-30%
A19: 28 | B19: 2 | C19: 2 | AE19: 28 | AF19: =IF(Sheet1!O15="1-3 years","2",IF(Sheet1!O15="more than 5 years","5",IF(Sheet1!O15="3-5 years","3","1"))) -> 2 | AG19: =IF(Sheet1!Q15="20%-30%","2",IF(Sheet1!Q15="10%-20%","1",IF(Sheet1!Q15="30%-40%","3"))) -> 2 | AH19: 2 | AJ19: 28 | AK19: 1-3 years | AL19: 20%-30%
A20: 25 | B20: 2 | C20: 2 | AE20: 25 | AF20: =IF(Sheet1!O16="1-3 years","2",IF(Sheet1!O16="more than 5 years","5",IF(Sheet1!O16="3-5 years","3","1"))) -> 2 | AG20: =IF(Sheet1!Q16="20%-30%","2",IF(Sheet1!Q16="10%-20%","1",IF(Sheet1!Q16="30%-40%","3"))) -> 2 | AH20: 2 | AJ20: 25 | AK20: 1-3 years | AL20: 20%-30%
A21: 27 | B21: 2 | C21: 2 | AE21: 27 | AF21: =IF(Sheet1!O17="1-3 years","2",IF(Sheet1!O17="more than 5 years","5",IF(Sheet1!O17="3-5 years","3","1"))) -> 2 | AG21: =IF(Sheet1!Q17="20%-30%","2",IF(Sheet1!Q17="10%-20%","1",IF(Sheet1!Q17="30%-40%","3"))) -> 2 | AH21: 2 | AJ21: 27 | AK21: 1-3 years | AL21: 20%-30%
A22: 28 | B22: 2 | C22: 2 | AE22: 28 | AF22: =IF(Sheet1!O18="1-3 years","2",IF(Sheet1!O18="more than 5 years","5",IF(Sheet1!O18="3-5 years","3","1"))) -> 2 | AG22: =IF(Sheet1!Q18="20%-30%","2",IF(Sheet1!Q18="10%-20%","1",IF(Sheet1!Q18="30%-40%","3"))) -> 2 | AH22: 2 | AJ22: 28 | AK22: 1-3 years | AL22: 20%-30%
A23: 27 | B23: 2 | C23: 2 | AE23: 27 | AF23: =IF(Sheet1!O19="1-3 years","2",IF(Sheet1!O19="more than 5 years","5",IF(Sheet1!O19="3-5 years","3","1"))) -> 2 | AG23: =IF(Sheet1!Q19="20%-30%","2",IF(Sheet1!Q19="10%-20%","1",IF(Sheet1!Q19="30%-40%","3"))) -> 2 | AH23: 2 | AJ23: 27 | AK23: 1-3 years | AL23: 20%-30%
A24: 29 | B24: 2 | C24: 2 | AE24: 29 | AF24: =IF(Sheet1!O20="1-3 years","2",IF(Sheet1!O20="more than 5 years","5",IF(Sheet1!O20="3-5 years","3","1"))) -> 2 | AG24: =IF(Sheet1!Q20="20%-30%","2",IF(Sheet1!Q20="10%-20%","1",IF(Sheet1!Q20="30%-40%","3"))) -> 2 | AH24: 2 | AJ24: 29 | AK24: 1-3 years | AL24: 20%-30%
A25: 26 | B25: 3 | C25: 2 | AE25: 26 | AF25: =IF(Sheet1!O21="1-3 years","2",IF(Sheet1!O21="more than 5 years","5",IF(Sheet1!O21="3-5 years","3","1"))) -> 3 | AG25: =IF(Sheet1!Q21="20%-30%","2",IF(Sheet1!Q21="10%-20%","1",IF(Sheet1!Q21="30%-40%","3"))) -> 2 | AH25: 2 | AJ25: 26 | AK25: 3-5 years | AL25: 20%-30%
A26: 29 | B26: 3 | C26: 2 | AE26: 29 | AF26: =IF(Sheet1!O22="1-3 years","2",IF(Sheet1!O22="more than 5 years","5",IF(Sheet1!O22="3-5 years","3","1"))) -> 3 | AG26: =IF(Sheet1!Q22="20%-30%","2",IF(Sheet1!Q22="10%-20%","1",IF(Sheet1!Q22="30%-40%","3"))) -> 2 | AH26: 2 | AJ26: 29 | AK26: 3-5 years | AL26: 20%-30%
A27: 24 | B27: 3 | C27: 2 | AE27: 24 | AF27: =IF(Sheet1!O23="1-3 years","2",IF(Sheet1!O23="more than 5 years","5",IF(Sheet1!O23="3-5 years","3","1"))) -> 3 | AG27: =IF(Sheet1!Q23="20%-30%","2",IF(Sheet1!Q23="10%-20%","1",IF(Sheet1!Q23="30%-40%","3"))) -> 2 | AH27: 2 | AJ27: 24 | AK27: 3-5 years | AL27: 20%-30%
... A45: 29 | B45: 3 | C45: 2 | AE45: 29 | AF45: =IF(Sheet1!O41="1-3 years","2",IF(Sheet1!O41="more than 5 years","5",IF(Sheet1!O41="3-5 years","3","1"))) -> 3 | AG45: =IF(Sheet1!Q41="20%-30%","2",IF(Sheet1!Q41="10%-20%","1",IF(Sheet1!Q41="30%-40%","3"))) -> 2 | AH45: 2 | AJ45: 29 | AK45: 3-5 years | AL45: 20%-30%

Sheet Sheet7
A1: Task 6: Dashboard Creation in Excel
B5: Equity Reasons | E5: Bonds Reasons | I5: What are your savings objectives? | J5: Count of What are your savings objectives? | N5: Investment Avenue | O5: Capital Appreciation | P5: Dividend | Q5: Liquidity | R5: Better Returns | S5: Fund Diversification | T5: Tax Benefits | U5: Assured Returns | V5: Safe Investment | W5: Tax Incentives | X5: Fixed Returns | Y5: High Interest Rates | Z5: Risk Free
B6: Row Labels | C6: Count of Reason_Equity | E6: Reason_Bonds | F6: Count of Reason_Bonds | I6: Education | J6: 3 | N6: Equity | O6: =COUNTIFS(Sheet1!$T:$T,O$5) -> 30 | P6: =COUNTIFS(Sheet1!$T:$T,P$5) -> 8 | Q6: =COUNTIFS(Sheet1!$T:$T,Q$5) -> 2 | R6: =COUNTIFS(Sheet1!$T:$T,R$5) -> 0 | S6: =COUNTIFS(Sheet1!$T:$T,S$5) -> 0 | T6: =COUNTIFS(Sheet1!$T:$T,T$5) -> 0 | U6: =COUNTIFS(Sheet1!$T:$T,U$5) -> 0 | V6: =COUNTIFS(Sheet1!$T:$T,V$5) -> 0 | ... Z6: =COUNTIFS(Sheet1!$T:$T,Z$5) -> 0
B7: Capital Appreciation | C7: 30 | E7: Assured Returns | F7: 26 | I7: Health Care | J7: 13 | N7: Mutual | O7: =COUNTIFS(Sheet1!$U:$U,O$5) -> 0 | P7: =COUNTIFS(Sheet1!$U:$U,P$5) -> 0 | Q7: =COUNTIFS(Sheet1!$U:$U,Q$5) -> 0 | R7: =COUNTIFS(Sheet1!$U:$U,R$5) -> 24 | S7: =COUNTIFS(Sheet1!$U:$U,S$5) -> 13 | T7: =COUNTIFS(Sheet1!$U:$U,T$5) -> 3 | U7: =COUNTIFS(Sheet1!$U:$U,U$5) -> 0 | V7: =COUNTIFS(Sheet1!$U:$U,V$5) -> 0 | ... Z7: =COUNTIFS(Sheet1!$U:$U,Z$5) -> 0
B8: Dividend | C8: 8 | E8: Safe Investment | F8: 13 | I8: Retirement Plan | J8: 24 | N8: Bonds | O8: =COUNTIFS(Sheet1!$V:$V,O$5) -> 0 | P8: =COUNTIFS(Sheet1!$V:$V,P$5) -> 0 | Q8: =COUNTIFS(Sheet1!$V:$V,Q$5) -> 0 | R8: =COUNTIFS(Sheet1!$V:$V,R$5) -> 0 | S8: =COUNTIFS(Sheet1!$V:$V,S$5) -> 0 | T8: =COUNTIFS(Sheet1!$V:$V,T$5) -> 0 | U8: =COUNTIFS(Sheet1!$V:$V,U$5) -> 26 | V8: =COUNTIFS(Sheet1!$V:$V,V$5) -> 13 | ... Z8: =COUNTIFS(Sheet1!$V:$V,Z$5) -> 0
B9: Liquidity | C9: 2 | E9: Tax Incentives | F9: 1 | I9: Grand Total | J9: 40 | N9: FD | O9: =COUNTIFS(Sheet1!$W:$W,O$5) -> 0 | P9: =COUNTIFS(Sheet1!$W:$W,P$5) -> 0 | Q9: =COUNTIFS(Sheet1!$W:$W,Q$5) -> 0 | R9: =COUNTIFS(Sheet1!$W:$W,R$5) -> 0 | S9: =COUNTIFS(Sheet1!$W:$W,S$5) -> 0 | T9: =COUNTIFS(Sheet1!$W:$W,T$5) -> 0 | U9: =COUNTIFS(Sheet1!$W:$W,U$5) -> 0 | V9: =COUNTIFS(Sheet1!$W:$W,V$5) -> 0 | ... Z9: =COUNTIFS(Sheet1!$W:$W,Z$5) -> 19
B10: Grand Total | C10: 40 | E10: Grand Total | F10: 40
I11: Source | J11: Count of Source
I12: Financial Consultants | J12: 16 | O12: Investment Avenue
B13: Mutual Reasons | E13: FD Reasons | I13: Internet | J13: 4 | N13: Values | O13: Bonds | P13: Equity | Q13: FD | R13: Mutual | S13: Grand Total
B14: Reason_Mutual | C14: Count of Reason_Mutual | E14: Reason_FD | F14: Count of Reason_FD | I14: Newspapers and Magazines | J14: 14 | N14: Sum of Capital Appreciation | O14: 0 | P14: 30 | Q14: 0 | R14: 0 | S14: 30
B15: Better Returns | C15: 24 | E15: Fixed Returns | F15: 18 | I15: Television | J15: 6 | N15: Sum of Dividend | O15: 0 | P15: 8 | Q15: 0 | R15: 0 | S15: 8
B16: Fund Diversification | C16: 13 | E16: High Interest Rates | F16: 3 | I16: Grand Total | J16: 40 | N16: Sum of Liquidity | O16: 0 | P16: 2 | Q16: 0 | R16: 0 | S16: 2
B17: Tax Benefits | C17: 3 | E17: Risk Free | F17: 19 | N17: Sum of Better Returns | O17: 0 | P17: 0 | Q17: 0 | R17: 24 | S17: 24
B18: Grand Total | C18: 40 | E18: Grand Total | F18: 40 | N18: Sum of Fund Diversification | O18: 0 | P18: 0 | Q18: 0 | R18: 13 | S18: 13
N19: Sum of Tax Benefits | O19: 0 | P19: 0 | Q19: 0 | R19: 3 | S19: 3
N20: Sum of Assured Returns | O20: 26 | P20: 0 | Q20: 0 | R20: 0 | S20: 26
N21: Sum of Safe Investment | O21: 13 | P21: 0 | Q21: 0 | R21: 0 | S21: 13
C22: Duration | D22: Count of Duration | N22: Sum of Tax Incentives | O22: 1 | P22: 0 | Q22: 0 | R22: 0 | S22: 1
C23: 1-3 years | D23: 18 | F23: Expect | G23: Count of Expect | N23: Sum of Fixed Returns | O23: 0 | P23: 0 | Q23: 18 | R23: 0 | S23: 18
C24: 3-5 years | D24: 19 | F24: 10%-20% | G24: 3 | N24: Sum of High Interest Rates | O24: 0 | P24: 0 | Q24: 3 | R24: 0 | S24: 3
C25: Less than 1 year | D25: 2 | F25: 20%-30% | G25: 32 | N25: Sum of Risk Free | O25: 0 | P25: 0 | Q25: 19 | R25: 0 | S25: 19
C26: More than 5 years | D26: 1 | F26: 30%-40% | G26: 5
C27: Grand Total | D27: 40 | F27: Grand Total | G27: 40

Sheet Sheet11
